blurryface/__init__.py
blurryface/blurryface_image.py
blurryface/blurryface_video.py
blurryface/__pycache__/__init__.cpython-37.pyc
blurryface/__pycache__/blurryface_image.cpython-37.pyc
blurryface/__pycache__/blurryface_video.cpython-37.pyc
blurryface-1.0.2.dist-info/METADATA
blurryface-1.0.2.dist-info/WHEEL
blurryface-1.0.2.dist-info/entry_points.txt
blurryface-1.0.2.dist-info/top_level.txt
blurryface-1.0.2.dist-info/RECORD
